{"swagger":"2.0","info":{"title":"HackerRank","description":"With HackerRank's API you can run codes in many different languages.","contact":{"name":"hackerrank","url":"https://www.hackerrank.com"},"version":null,"x-logo":"https://s3.amazonaws.com/mashape-production-logos/apis/53aa60eee4b0a9b1348dbd16_medium","x-mashape-categories":["Tools"],"x-origin":{"format":"mashape","url":"https://market.mashape.com/hackerrank/hackerrank"}},"host":"hackerrank-hackerrank.p.mashape.com","basePath":"","paths":{"/https://api.hackerrank.com/checker/submission.json":{"post":{"description":"Allows users to use the HackerRank code checker for their own purposes. Submit source code, which is compiled and run against a list of provided test cases.","operationId":"code-checker","consumes":["application/json"],"produces":["application/json"],"responses":{"200":{"description":null,"schema":"#/definitions/Resource"}}}},"/https://api.hackerrank.com/checker/languages.json":{"get":{"description":"This method provides you with information regarding the language codes which our code checker supports","operationId":"languages"}}},"definitions":{"Resource":{"type":"object","properties":{"result":{"$ref":"#/definitions/Result"}}},"Result":{"type":"object","properties":{"callback_url":{"type":"string"},"censored_compile_message":{"type":"string"},"censored_stderr":{"type":"array","items":{"type":"string"}},"codechecker_hash":{"type":"string"},"compilemessage":{"type":"string"},"created_at":{"type":"string"},"custom_score":{"type":"string"},"custom_status":{"type":"string"},"diff_status":{"type":"string"},"hash":{"type":"string"},"memory":{"type":"array","items":{"type":"integer"}},"message":{"type":"array","items":{"type":"string"}},"result":{"type":"integer"},"server":{"type":"string"},"signal":{"type":"array","items":{"type":"integer"}},"stderr":{"type":"array","items":{"type":"string"}},"stdout":{"type":"array","items":{"type":"string"}},"time":{"type":"array","items":{"type":"integer"}}}},"Resource_0":{"type":"object"}}}