{"swagger":"2.0","info":{"title":"Indian colleges and universities","description":"API endpoint for colleges and universities in India.\r\nGet  access to information like name, ph number, city, state, address.","contact":{"name":"n4nagappan"},"version":null,"x-logo":"https://s3.amazonaws.com/mashape-production-logos/apis/5460ae69e4b0c25d77201151_medium","x-mashape-categories":["Education"],"x-origin":{"format":"mashape","url":"https://market.mashape.com/n4nagappan/indian-colleges-and-universities"}},"host":"indian-colleges.p.mashape.com","basePath":"","paths":{"/v1/colleges":{"get":{"description":"gets  name, ph number, city, state, address and email  of colleges/universities located in India","operationId":"v1-colleges","produces":["application/json"],"parameters":[{"name":"city","in":"query","description":"filter by city"},{"name":"name","in":"query","description":"filter by college names that contain a given word"},{"name":"page","in":"query","description":"set page number. ( default is 0 )"},{"name":"state","in":"query","description":"filter by state"}],"responses":{"200":{"description":null,"schema":{"type":"array"}}}}}},"definitions":{"Resource":{"type":"object","properties":{"_id":{"type":"string"},"website":{"type":"string"},"city":{"type":"string"},"tel":{"type":"string"},"name":{"type":"string"},"state":{"type":"string"},"address":{"type":"string"},"email":{"type":"string"}}}}}