{"swagger":"2.0","info":{"title":"instant PDF","description":"This API allows generating PDFs using JSON markup. The API accepts HTTP POST requests and returns PDF documents. \r\n\r\nFurther documentation is available at https://github.com/yogthos/instant-pdf","contact":{"name":"yogthos","url":"https://github.com/yogthos/instant-pdf"},"version":null,"x-logo":"https://s3.amazonaws.com/mashape-production-logos/apis/53aa3201e4b051a76d23f158_medium","x-mashape-categories":["Data"],"x-origin":{"format":"mashape","url":"https://market.mashape.com/yogthos/instant-pdf"}},"host":"yogthos.p.mashape.com","basePath":"","paths":{"/":{"post":{"description":"","operationId":"generating-a-pdf","consumes":["application/json"]}}},"definitions":{"Resource_0":{"type":"object"}}}