{"swagger":"2.0","info":{"title":"IP Address Geolocation","description":"This API returns the location of an IP address (country, region, city, zipcode, latitude and longitude) and the associated timezone in JSON or XML format.","contact":{"name":"chrislim","url":"http://www.ipinfodb.com"},"version":null,"x-logo":"https://s3.amazonaws.com/mashape-production-logos/apis/53aa359ae4b059614033f3ba_medium","x-mashape-categories":["Location"],"x-origin":{"format":"mashape","url":"https://market.mashape.com/chrislim/ip-address-geolocation"}},"host":"chrislim2888-ip-address-geolocation.p.mashape.com","basePath":"","paths":{"/":{"get":{"description":"Returns the location of an IP address (country, region, city, zipcode, latitude and longitude) and the associated timezone in JSON or XML format.","operationId":"getiplocation","parameters":[{"name":"format","in":"query","description":"It supports json and xml response format.","required":true},{"name":"ip","in":"query","description":"IP Address. It supports both IPv4 and IPv6 address format.","required":true}]}}},"definitions":{"Resource_0":{"type":"object"}}}