{"swagger":"2.0","info":{"title":"nlpTools","description":"Text processing framework to analyse Natural Language. It is especially focused on text classification and sentiment analysis of online news media (general-purpose, multiple topics).","contact":{"name":"atrilla","url":"http://nlptools.atrilla.net"},"version":null,"x-logo":"https://s3.amazonaws.com/mashape-production-logos/apis/53aa3b50e4b0a798dbd19967_medium","x-mashape-categories":["Tools"],"x-origin":{"format":"mashape","url":"https://market.mashape.com/atrilla/nlptools"}},"host":"atrilla-nlptools.p.mashape.com","basePath":"","paths":{"/":{"post":{"description":"Sentiment analysis of online news media (general-purpose, multiple topics). See \"http://nlptools.atrilla.net/web/api.php\" for more details.","operationId":"sentiment-analysis","consumes":["application/json"]}}},"definitions":{"Resource_0":{"type":"object"}}}