{"swagger":"2.0","info":{"title":"pdf2txt","description":"Convert PDF to text","contact":{"name":"bakhshandeh"},"version":null,"x-logo":"https://s3.amazonaws.com/mashape-production-logos/apis/555a65bfe4b0df756678f95a_medium","x-mashape-categories":["Tools"],"x-origin":{"format":"mashape","url":"https://market.mashape.com/bakhshandeh/pdf2txt"}},"host":"bakhshandeh-pdf2txt-v1.p.mashape.com","basePath":"","paths":{"/pdf2txt":{"post":{"description":"pdf2txt","operationId":"pdf2txt","consumes":["application/json"]}}}}