{"swagger":"2.0","info":{"title":"rome2rio-10","description":"NOTE: This is version 1.0 of our API. Please use the latest version instead.","contact":{"name":"rome2rio","url":"http://www.rome2rio.com"},"version":null,"x-logo":"https://s3.amazonaws.com/mashape-production-logos/apis/53aa316ae4b002874719ff01_medium","x-mashape-categories":["Travel"],"x-origin":{"format":"mashape","url":"https://market.mashape.com/rome2rio/rome2rio-10"}},"host":"rome2rio10.p.mashape.com","basePath":"","paths":{"/GetRoutes":{"get":{"description":"provide routes options from one point to another","operationId":"getroutes","produces":["application/json"],"parameters":[{"name":"dName","in":"query","description":"Destination display name","required":true},{"name":"dPos","in":"query","description":"Destination latitude,longitude (comma separated)"},{"name":"oName","in":"query","description":"Origin display name","required":true},{"name":"oPos","in":"query","description":"Origin latitude,longitude (comma separated)"}],"responses":{"200":{"description":null,"schema":"#/definitions/Resource"}}}}},"definitions":{"Resource":{"type":"object","properties":{"airlines":{"type":"array","items":{"$ref":"#/definitions/Airline"}},"airports":{"type":"array","items":{"$ref":"#/definitions/Airport"}},"routes":{"type":"array","items":{"$ref":"#/definitions/Route"}}}},"Leg":{"type":"object","properties":{"url":{"type":"string"},"hops":{"type":"array","items":{"$ref":"#/definitions/Hop"}}}},"Hop":{"type":"object","properties":{"agency":{"type":"string"},"duration":{"type":"integer"},"frequency":{"type":"string"},"line":{"type":"string"},"path":{"type":"string"},"sName":{"type":"string"},"sPos":{"type":"string"},"tName":{"type":"string"},"tPos":{"type":"string"},"vehicle":{"type":"string"}}},"Airline":{"type":"object","properties":{"code":{"type":"string"},"name":{"type":"string"},"url":{"type":"string"}}},"Airport":{"type":"object","properties":{"code":{"type":"string"},"name":{"type":"string"},"pos":{"type":"string"}}},"Itinerarie":{"type":"object","properties":{"legs":{"type":"array","items":{"$ref":"#/definitions/Leg"}}}},"Segment":{"type":"object","properties":{"distance":{"type":"integer"},"duration":{"type":"integer"},"kind":{"type":"string"},"sName":{"type":"string"},"sPos":{"type":"string"},"tName":{"type":"string"},"tPos":{"type":"string"},"itineraries":{"type":"array","items":{"$ref":"#/definitions/Itinerarie"}}}},"Route":{"type":"object","properties":{"segments":{"type":"array","items":{"$ref":"#/definitions/Segment"}}}}}}