{"swagger":"2.0","info":{"title":"Visual Context Graph","description":"Build a graph with words connected to other words. Diagram information for visualizing concepts or mind maps.","contact":{"name":"twinword","url":"https://www.twinword.com"},"version":null,"x-logo":"https://s3.amazonaws.com/mashape-production-logos/apis/53aa5082e4b0a9b1348da681_medium","x-mashape-categories":["Tools","Data"],"x-origin":{"format":"mashape","url":"https://market.mashape.com/twinword/visual-context-graph"}},"host":"twinword-visual-context-graph.p.mashape.com","basePath":"","paths":{"/visualize/":{"get":{"description":"Diagram information for visualizing concepts or mind maps.","operationId":"visualize-get","produces":["application/json"],"parameters":[{"name":"entry","in":"query","description":"Type a word to see the words connected to it","required":true}],"responses":{"200":{"description":null,"schema":"#/definitions/Resource"}}},"post":{"description":"Diagram information for visualizing concepts or mind maps.","operationId":"visualize-post","consumes":["application/json"],"produces":["application/json"],"parameters":[{"name":"entry","in":"query","description":"Type a word to see the words connected to it","required":true}],"responses":{"200":{"description":null,"schema":"#/definitions/Resource"}}}}},"definitions":{"Resource":{"type":"object","properties":{"entry":{"type":"string"},"context":{"type":"array","items":{"type":"string"}},"result_code":{"type":"string"},"result_msg":{"type":"string"},"relation":{"type":"array","items":{"$ref":"#/definitions/Relation"}}}},"Relation":{"type":"object","properties":{"acoustic":{"type":"string"},"acoustics":{"type":"string"},"alarm":{"type":"string"},"alert":{"type":"string"},"amplifier":{"type":"string"},"amplitude":{"type":"string"},"attune":{"type":"string"},"audio":{"type":"string"},"auditory":{"type":"string"},"beep":{"type":"string"},"bell":{"type":"string"},"blare":{"type":"string"},"blowing":{"type":"string"},"brassy":{"type":"string"},"bray":{"type":"string"},"breaking":{"type":"string"},"cacophonous":{"type":"string"},"chirp":{"type":"string"},"chord":{"type":"string"},"click":{"type":"string"},"cassette":{"type":"string"},"commentary":{"type":"string"},"converter":{"type":"string"},"dubbing":{"type":"string"},"playback":{"type":"string"},"recorder":{"type":"string"},"recording":{"type":"string"},"sonic":{"type":"string"},"studio":{"type":"string"},"subtitle":{"type":"string"},"tape":{"type":"string"},"transcription":{"type":"string"},"video":{"type":"string"},"voice":{"type":"string"},"ditto":{"type":"string"},"earshot":{"type":"string"},"echo":{"type":"string"},"hearing":{"type":"string"},"iterate":{"type":"string"},"mimic":{"type":"string"},"repeat":{"type":"string"},"repeatedly":{"type":"string"},"resonance":{"type":"string"},"resonate":{"type":"string"},"resound":{"type":"string"},"reverberate":{"type":"string"},"reverberation":{"type":"string"},"sonar":{"type":"string"},"accompaniment":{"type":"string"},"album":{"type":"string"},"aria":{"type":"string"},"artist":{"type":"string"},"artistic":{"type":"string"},"atonal":{"type":"string"},"ballroom":{"type":"string"},"blandness":{"type":"string"},"blues":{"type":"string"},"cantata":{"type":"string"},"cello":{"type":"string"},"choreograph":{"type":"string"},"choreography":{"type":"string"},"chorus":{"type":"string"},"chromatic":{"type":"string"},"classical":{"type":"string"},"compose":{"type":"string"},"composer":{"type":"string"},"barograph":{"type":"string"},"barometer":{"type":"string"},"gramophone":{"type":"string"},"phonograph":{"type":"string"},"subliminal":{"type":"string"},"accent":{"type":"string"},"aloud":{"type":"string"},"alto":{"type":"string"},"audible":{"type":"string"},"baritone":{"type":"string"},"cackle":{"type":"string"},"dupe":{"type":"string"},"dysphonia":{"type":"string"},"effeminate":{"type":"string"},"emotionless":{"type":"string"},"gruff":{"type":"string"},"hoarse":{"type":"string"},"homophonic":{"type":"string"},"husky":{"type":"string"},"impersonate":{"type":"string"},"intrusive":{"type":"string"}}}}}